setup.py
b_g_distributions/Binomialdistribution.py
b_g_distributions/Gaussiandistribution.py
b_g_distributions/Generaldistribution.py
b_g_distributions/__init__.py
b_g_distributions.egg-info/PKG-INFO
b_g_distributions.egg-info/SOURCES.txt
b_g_distributions.egg-info/dependency_links.txt
b_g_distributions.egg-info/not-zip-safe
b_g_distributions.egg-info/top_level.txt