Metadata-Version: 1.0
Name: b-g-distributions
Version: 0.4
Summary: Gaussian distributions
Home-page: UNKNOWN
Author: UNKNOWN
Author-email: UNKNOWN
License: UNKNOWN
Platform: UNKNOWN
